jitcache.py
jitcache-0.32.dist-info/LICENSE
jitcache-0.32.dist-info/METADATA
jitcache-0.32.dist-info/WHEEL
jitcache-0.32.dist-info/top_level.txt
jitcache-0.32.dist-info/RECORD
