Metadata-Version: 2.1
Name: jitcache
Version: 0.32
Summary: jitcache is a just-in-time key-value cache that isthread/process safe
Home-page: https://github.com/sjtrny/jitcache
Author: Stephen Tierney
Author-email: sjtrny@gmail.com
License: UNKNOWN
Keywords: cache jit key value dictionary thread process
Platform: UNKNOWN
Classifier: License :: OSI Approved :: MIT License
Requires-Python: >=3
